giteo/__init__.py
giteo/__main__.py
giteo-1.0.0.dist-info/LICENSE
giteo-1.0.0.dist-info/METADATA
giteo-1.0.0.dist-info/WHEEL
giteo-1.0.0.dist-info/dependency_links.txt
giteo-1.0.0.dist-info/entry_points.txt
giteo-1.0.0.dist-info/top_level.txt
giteo-1.0.0.dist-info/RECORD
