Metadata-Version: 2.1
Name: giteo
Version: 1.0.0
Summary: Giteo: A CLI Client for GitHub's Git.io URL Shortener
Home-page: https://github.com/BoxingOctopus/giteo
Author: Ryan Draga
Author-email: ryan.draga@boxingoctop.us
License: Apache-2.0
Download-URL: https://github.com/BoxingOctopus/giteo/archive/1.0.0.tar.gz
Platform: UNKNOWN
Classifier: License :: OSI Approved :: Apache Software License
Classifier: Programming Language :: Python :: 3
Classifier: Programming Language :: Python :: 3.7
Classifier: Programming Language :: Python :: 3.8
Classifier: Programming Language :: Python :: 3.9
Requires-Python: >=3.7
Requires-Dist: certifi (==2020.12.5)
Requires-Dist: chardet (==4.0.0)
Requires-Dist: click (==7.1.2)
Requires-Dist: idna (==2.10)
Requires-Dist: requests (==2.25.1)
Requires-Dist: urllib3 (==1.26.4)
